osgeonorge/__init__.py
osgeonorge/__main__.py
osgeonorge/geonorge.py
osgeonorge/grassgis.py
osgeonorge/postgis.py
osgeonorge/postgres.py
osgeonorge/sosi.py
osgeonorge/utils.py
osgeonorge-0.2.2.dist-info/WHEEL
osgeonorge-0.2.2.dist-info/METADATA
osgeonorge-0.2.2.dist-info/RECORD
