Metadata-Version: 2.1
Name: osgeonorge
Version: 0.2.2
Summary: Tools and functions for interacting with geonorge.no
Keywords: geonorge,osgeo,gdal,postgis,sosi,fyba,etl,elt,grass gis
Author-email: Stefan Blumentrath <stefan.blumentrath@nina.no>
Classifier: Topic :: Scientific/Engineering :: GIS
Classifier: Intended Audience :: Developers
Classifier: Development Status :: 4 - Beta
Classifier: Natural Language :: English
Classifier: License :: OSI Approved :: GNU General Public License v3 or later (GPLv3+)
Classifier: Programming Language :: Python :: 3.6
Requires-Dist: requests
Requires-Dist: psycopg2
Requires-Dist: GDAL
Requires-Dist: grass_session
Requires-Dist: pytest ; extra == "test"
Requires-Dist: pytest-cov ; extra == "test"
Requires-Dist: requests ; extra == "test"
Requires-Dist: psycopg2 ; extra == "test"
Requires-Dist: GDAL ; extra == "test"
Requires-Dist: grass_session ; extra == "test"
Provides-Extra: test
